rockstaa/__init__.py
rockstaa-0.1.0.dist-info/METADATA
rockstaa-0.1.0.dist-info/WHEEL
rockstaa-0.1.0.dist-info/top_level.txt
rockstaa-0.1.0.dist-info/RECORD
