Metadata-Version: 2.1
Name: rockstaa
Version: 0.1.0
Summary: About Rahul
Home-page: https://github.com/amalrajan/rockstaa
Author: Amal Rajan
Author-email: amalrajan@outlook.com
License: MIT
